pawprint/__init__.py
pawprint/sessions.py
pawprint/statistics.py
pawprint/tracker.py
pawprint-2.1.1.dist-info/LICENSE
pawprint-2.1.1.dist-info/METADATA
pawprint-2.1.1.dist-info/WHEEL
pawprint-2.1.1.dist-info/top_level.txt
pawprint-2.1.1.dist-info/RECORD
