Metadata-Version: 2.1
Name: pawprint
Version: 2.1.1
Summary: A flexible event tracker for rapid analysis.
Home-page: http://github.com/qcaudron/pawprint
Author: Quentin CAUDRON
Author-email: quentincaudron@gmail.com
License: MIT
Platform: UNKNOWN
Requires-Python: >=3.5
Requires-Dist: pandas (>=0.19)
Requires-Dist: sqlalchemy (>=1.0)
Requires-Dist: psycopg2 (>=2.4)
